Metadata-Version: 2.1
Name: stsex
Version: 0.0
Summary: stsex
Author-email: ilapronin0700@gmail.com
